[
  {
    "systolic": 121,
    "diastolic": 80,
    "pulse": 123,
    "notes": "",
    "dateTime": "2025/9/24 19:33:02"
  },
  {
    "systolic": 139,
    "diastolic": 76,
    "pulse": 96,
    "notes": "",
    "dateTime": "2025/9/12 19:25:09"
  },
  {
    "systolic": 122,
    "diastolic": 72,
    "pulse": 73,
    "notes": "",
    "dateTime": "2025/9/3 00:24:40"
  },
  {
    "systolic": 139,
    "diastolic": 77,
    "pulse": 78,
    "notes": "",
    "dateTime": "2025/9/1 14:55:04"
  },
  {
    "systolic": 131,
    "diastolic": 76,
    "pulse": 77,
    "notes": "",
    "dateTime": "2025/8/30 15:23:25"
  },
  {
    "systolic": 130,
    "diastolic": 72,
    "pulse": 76,
    "notes": "",
    "dateTime": "2025/8/29 23:59:21"
  },
  {
    "systolic": 142,
    "diastolic": 78,
    "pulse": 72,
    "notes": "",
    "dateTime": "2025/8/28 23:24:53"
  },
  {
    "systolic": 120,
    "diastolic": 76,
    "pulse": 88,
    "notes": "",
    "dateTime": "2025/8/26 19:43:45"
  },
  {
    "systolic": 119,
    "diastolic": 81,
    "pulse": 80,
    "notes": "",
    "dateTime": "2025/8/25 20:37:38"
  },
  {
    "systolic": 131,
    "diastolic": 78,
    "pulse": 81,
    "notes": "",
    "dateTime": "2025/8/25 09:23:16"
  },
  {
    "systolic": 122,
    "diastolic": 85,
    "pulse": 77,
    "notes": "",
    "dateTime": "2025/8/24 22:52:48"
  },
  {
    "systolic": 131,
    "diastolic": 71,
    "pulse": 74,
    "notes": "",
    "dateTime": "2025/8/24 21:47:39"
  }
]